amr_distributions
