Metadata-Version: 1.0
Name: amr-distributions
Version: 0.4
Summary: Gaussian distributions
Home-page: UNKNOWN
Author: Amro Walid
Author-email: amro.walid.mo@gmail.com
License: UNKNOWN
Platform: UNKNOWN
